hata/main/commands/init/__init__.py
hata/main/commands/init/app_creator.py
hata/main/commands/init/app_entry.py
hata/main/commands/init/callback.py
hata/main/commands/init/constants.py
hata/main/commands/init/utils.py
hata_init-0.1.0.dist-info/WHEEL
hata_init-0.1.0.dist-info/METADATA
hata_init-0.1.0.dist-info/RECORD
