Metadata-Version: 2.1
Name: hata-init
Version: 0.1.0
Summary: A cli plugin for hata which allows you to make bots fast
License: MIT
Author: WizzyGeek
Author-email: 51919967+WizzyGeek@users.noreply.github.com
Requires-Python: >=3.6,<4.0
Classifier: License :: OSI Approved :: MIT License
Classifier: Programming Language :: Python :: 3
Classifier: Programming Language :: Python :: 3.10
Classifier: Programming Language :: Python :: 3.6
Classifier: Programming Language :: Python :: 3.7
Classifier: Programming Language :: Python :: 3.8
Classifier: Programming Language :: Python :: 3.9
Requires-Dist: hata (>=1.2.8,<2.0.0)
Requires-Dist: typer (>=0.4.1,<0.5.0)
